msweb/__init__.py
msweb/admin.py
msweb/apps.py
msweb/tests.py
msweb/urls.py
msweb/forms/__init__.py
msweb/forms/contact_form.py
msweb/forms/form.py
msweb/forms/login_form.py
msweb/forms/model_form.py
msweb/forms/multi_forms.py
msweb/forms/widgets/__init__.py
msweb/forms/widgets/checkbox_input.py
msweb/forms/widgets/clearable_file_input.py
msweb/forms/widgets/date_input.py
msweb/forms/widgets/date_time_input.py
msweb/forms/widgets/email_input.py
msweb/forms/widgets/file_input.py
msweb/forms/widgets/hidden_input.py
msweb/forms/widgets/multiple_hidden_input.py
msweb/forms/widgets/null_boolean_input.py
msweb/forms/widgets/number_input.py
msweb/forms/widgets/password_input.py
msweb/forms/widgets/select_date_widget.py
msweb/forms/widgets/text_input.py
msweb/forms/widgets/textarea.py
msweb/forms/widgets/time_input.py
msweb/forms/widgets/url_input.py
msweb/migrations/__init__.py
msweb/views/__init__.py
msweb/views/template_view.py
muses_msweb-0.1.1601030966.dist-info/METADATA
muses_msweb-0.1.1601030966.dist-info/WHEEL
muses_msweb-0.1.1601030966.dist-info/top_level.txt
muses_msweb-0.1.1601030966.dist-info/RECORD
